qds_app/__init__.py
qds_app/_version.py
qds_app/mako_template.py
qds_app/migrations.py
qds_app/qds_app.py
qds_app/revision.py
qds_app-0.5.0.dist-info/DESCRIPTION.rst
qds_app-0.5.0.dist-info/METADATA
qds_app-0.5.0.dist-info/metadata.json
qds_app-0.5.0.dist-info/RECORD
qds_app-0.5.0.dist-info/top_level.txt
qds_app-0.5.0.dist-info/WHEEL
tests/__init__.py
tests/test_integration.py
tests/test_migration.py
