Metadata-Version: 2.0
Name: qds-app
Version: 0.5.0
Summary: An egg to add migrations to your project
Home-page: https://github.com/vrajat/qds_app.git
Author: Rajat Venkatesh
Author-email: rvenkatesh@qubole.com
License: UNKNOWN
Platform: UNKNOWN
Requires-Dist: mako (==1.0.4)
